siege.py
siege_cli-1.0.0.dist-info/METADATA
siege_cli-1.0.0.dist-info/WHEEL
siege_cli-1.0.0.dist-info/entry_points.txt
siege_cli-1.0.0.dist-info/top_level.txt
siege_cli-1.0.0.dist-info/RECORD
