Metadata-Version: 2.4
Name: siege-cli
Version: 1.0.0
Summary: A CLI tool for interacting with HC's Siege website
Author: strawberry-p
License-Expression: GPL-3.0-or-later
Requires-Python: >=3.8
Requires-Dist: argparse>=1.3.0
Requires-Dist: beautifulsoup4>=4.10.2
Requires-Dist: requests>=2.29.0
